{
  "name": "North West Round Robin (Carlisle-Preston-Leeds-Carlisle)",
  "url": "http://www.railrover.org/pages/north-west-round-robin.html",
  "RRT": "Ranger",
  "Region": ["North West", "Yorkshire and the Humber"],
  "Country": ["England"],
  "description": "NORTH WEST ROUND ROBIN Unlimited travel for one day with weekday time restrictions from anywhere in any direction on the route between Carlisle-Leeds-Blackburn-Preston-Carlisle plus Bradford Forster Square and includes the Settle and Carlisle and the Carnforth-Skipton lines as well as the West Coast Main Line between Carlisle and Preston.",
  "fares_1_day": {
    "valid_from": "Last Updated: Sunday 2nd March 2025",
    "duration": "1 Day",
    "multi_days_valid": 1,
    "total_duration": 1,
    "travelclass": "Standard",
    "adult": "£51.50",
    "child": "£25.75",
    "railcards": [
      { "type": "16-17 Saver", "price": "£25.75" },
      { "type": "16-25 Railcard", "price": "£34.25" },
      { "type": "26-30 Railcard", "price": "£34.25" },
      { "type": "Senior Railcard", "price": "£34.25" },
      { "type": "Disabled Persons Railcard", "price": "£34.25" },
      { "type": "Two Together Railcard", "price": "£34.25" },
      { "type": "Family & Friends Railcard", "price": "£34.25" },
      { "type": "Family & Friends Child Railcard", "price": "£9.75" },
      { "type": "HM Forces/Veterans Railcard", "price": "£34.25" },
      { "type": "HM Forces/Veterans Child Railcard", "price": "£9.75" }
    ]
  },
  "previous_fares_1_day": [
    { "year": 2024, "adult": "£49.20", "child": "", "Family & Friends Child Railcard": "", "16-17 Railcard": "", "16-25 Railcard": "", "26-30 Railcard": "", "Senior Railcard": "", "Disabled Persons Railcard": "", "Two Together Railcard": "", "HM Forces/Veterans Railcard": "", "Family & Friends Railcard": "" },
    { "year": 2023, "adult": "£46.90", "child": "", "Family & Friends Child Railcard": "", "16-17 Railcard": "", "16-25 Railcard": "", "26-30 Railcard": "", "Senior Railcard": "", "Disabled Persons Railcard": "", "Two Together Railcard": "", "HM Forces/Veterans Railcard": "", "Family & Friends Railcard": "" },
    { "year": 2022, "adult": "£44.30", "child": "", "Family & Friends Child Railcard": "", "16-17 Railcard": "", "16-25 Railcard": "", "26-30 Railcard": "", "Senior Railcard": "", "Disabled Persons Railcard": "", "Two Together Railcard": "", "HM Forces/Veterans Railcard": "", "Family & Friends Railcard": "" },
    { "year": 2021, "adult": "£41.70", "child": "", "Family & Friends Child Railcard": "", "16-17 Railcard": "", "16-25 Railcard": "", "26-30 Railcard": "", "Senior Railcard": "", "Disabled Persons Railcard": "", "Two Together Railcard": "", "HM Forces/Veterans Railcard": "", "Family & Friends Railcard": "" },
    { "year": 2020, "adult": "£41.70", "child": "", "Family & Friends Child Railcard": "", "16-17 Railcard": "", "16-25 Railcard": "", "26-30 Railcard": "", "Senior Railcard": "", "Disabled Persons Railcard": "", "Two Together Railcard": "", "HM Forces/Veterans Railcard": "", "Family & Friends Railcard": "" },
    { "year": 2019, "adult": "£40.50", "child": "", "Family & Friends Child Railcard": "", "16-17 Railcard": "", "16-25 Railcard": "", "26-30 Railcard": "", "Senior Railcard": "", "Disabled Persons Railcard": "", "Two Together Railcard": "", "HM Forces/Veterans Railcard": "", "Family & Friends Railcard": "" },
    { "year": 2018, "adult": "£39.30", "child": "", "Family & Friends Child Railcard": "", "16-17 Railcard": "", "16-25 Railcard": "", "26-30 Railcard": "", "Senior Railcard": "", "Disabled Persons Railcard": "", "Two Together Railcard": "", "HM Forces/Veterans Railcard": "", "Family & Friends Railcard": "" },
    { "year": 2014, "adult": "£36.50", "child": "", "Family & Friends Child Railcard": "", "16-17 Railcard": "", "16-25 Railcard": "", "26-30 Railcard": "", "Senior Railcard": "", "Disabled Persons Railcard": "", "Two Together Railcard": "", "HM Forces/Veterans Railcard": "", "Family & Friends Railcard": "" },
    { "year": 2011, "adult": "£32.00", "child": "", "Family & Friends Child Railcard": "", "16-17 Railcard": "", "16-25 Railcard": "", "26-30 Railcard": "", "Senior Railcard": "", "Disabled Persons Railcard": "", "Two Together Railcard": "", "HM Forces/Veterans Railcard": "", "Family & Friends Railcard": "" }
  ],
  "time_restrictions": "Mon to Fri: valid from 09:00 but Two Together railcard not valid until 09:30. No restrictions at weekends or bank holidays.",
  "route_restrictions": "Unlimited travel for one day with weekday time restrictions from anywhere in any direction on the route between Carlisle-Leeds-Blackburn-Preston-Carlisle plus Bradford Forster Square and includes the Settle and Carlisle and the Carnforth-Skipton lines as well as the West Coast Main Line between Carlisle and Preston.",
  "train_operators_valid_on": [
    "Avanti West Coast",
    "Northern",
    "TransPennine Express"
  ],
  "where_to_buy": [
    "Online: Not available",
    "Train conductor: Available",
    "Station ticket office: Available",
    "Ticket Vending Machine (TVM): Some Northern, Avanti West Coast, and LNER TVMs sell these tickets (see notes)",
    "Valid ticket to travel is required unless boarded at a station without ticket-issuing facilities"
  ],
  "stations": [
    "Accrington",
    "Apperley Bridge",
    "Appleby",
    "Armathwaite",
    "Bamber Bridge",
    "Bentham",
    "Bingley",
    "Blackburn",
    "Bradford Forster Square",
    "Bradford Interchange",
    "Bramley",
    "Burnley Manchester Road",
    "Carlisle",
    "Carnforth",
    "Cherry Tree",
    "Clapham",
    "Cononley",
    "Crossflatts",
    "Dent",
    "Frizinghall",
    "Gargrave",
    "Garsdale",
    "Giggleswick",
    "Halifax",
    "Hapton",
    "Hebden Bridge",
    "Hellifield",
    "Horton-in-Ribblesdale",
    "Huncoat",
    "Keighley",
    "Kirkby Stephen",
    "Kirkstall Forge",
    "Lancaster",
    "Langwathby",
    "Lazonby & Kirkoswald",
    "Leeds",
    "Long Preston",
    "Lostock Hall",
    "Low Moor",
    "Mill Hill",
    "Mytholmroyd",
    "New Pudsey",
    "Oswaldtwistle",
    "Oxenholme Lake District",
    "Penrith North Lakes",
    "Pleasington",
    "Preston",
    "Ribblehead",
    "Rishton",
    "Rose Grove",
    "Saltaire",
    "Settle",
    "Shipley",
    "Skipton",
    "Sowerby Bridge",
    "Steeton & Silsden",
    "Wennington"
  ],
  "route_map_images": [
    "ticket_maps/North_West_Round_Robin_Carlisle-Preston-Leeds-Carlisle_north_west_round_robin.gif"
  ]
}